{
    "type": "Feature",
    "geometry": {
        "type": "Point",
        "coordinates": [18.583747, 53.039949]
    },
    "properties": {
        "type": "historical-venue",
        "name": "Hala Widowiskowo-Sportowa OSiR II",
        "description": "Dr Szuman's Assisted Living Facility, where [DFW Debut Show](@/e/dfw/2015-06-20-dfw-showcase.md) and [Tournament of Dreams I](@/e/dfw/2016-06-11-dfw-tournament-of-dreams-1.md) were held.",
        "orgs": ["dfw"]
    }
}
