{
  "type": "FeatureCollection",
  "generator": "overpass-turbo",
  "copyright": "The data included in this document is from www.openstreetmap.org. The data is made available under ODbL.",
  "timestamp": "2025-06-04T22:42:32Z",
  "features": [
    {
      "type": "Feature",
      "geometry": {
          "type": "Point",
          "coordinates": [18.648471, 54.364557]
      },
      "properties": {
          "type": "venue",
          "slug": "b90",
          "name": "B90",
          "description": "B90 club, where [KPW](@/o/kpw.md) held [Szlamfest](@/e/kpw/2017-02-04-kpw-szlamfest.md), [Arena 9](@/e/kpw/2018-03-10-kpw-arena-9.md) and [Arena 14](@/e/kpw/2019-06-15-kpw-arena-14.md).",
          "orgs": ["kpw"]
      }
    },
    {
        "type": "Feature",
        "geometry": {
            "type": "Point",
            "coordinates": [18.648866, 54.364814]
        },
        "properties": {
            "type": "venue",
            "slug": "plenum",
            "name": "Plenum",
            "description": "Plenum Hall, where [Lucha Libre Extravaganza](@/e/ppw/2025-05-16-ppw-lucha-libre-extravaganza.md) was held (above Drizzly Grizzly club).",
            "orgs": ["ppw"]
        }
    },
    {
        "type": "Feature",
        "geometry": {
            "type": "Point",
            "coordinates": [18.651491, 54.362442]
        },
        "properties": {
            "type": "venue",
            "slug": "chill-out-zone",
            "name": "Mystic Festival's Chill Out Zone",
            "description": "Mystic Festival's Chill Out Zone, where [More Brutal Than Metal](@/e/ppw/2025-06-04-ppw-mystic-more-brutal-than-metal.md) was held.",
            "orgs": ["ppw"]
        }
    }
  ]
}
