{
    "type": "Feature",
    "geometry": {
        "type": "Point",
        "coordinates": [21.059890, 52.164844]
    },
    "properties": {
        "type": "historical-venue",
        "name": "Ognicho",
        "description": "A small clearing in the woods, where [PpW](@/o/ppw.md) held [Kiedyś Będzie Lepiej](@/e/ppw/2019-07-13-ppw-kiedys-bedzie-lepiej.md) and [Dark Show](@/e/ppw/2019-09-27-ppw-dark-show.md).",
        "orgs": ["kpw"]
    }
}
